pyflag/__init__.py
pyflag/bindings.cpython-38-darwin.so
pyflag-1.0.0.dist-info/LICENSE.txt
pyflag-1.0.0.dist-info/METADATA
pyflag-1.0.0.dist-info/WHEEL
pyflag-1.0.0.dist-info/top_level.txt
pyflag-1.0.0.dist-info/RECORD
