Metadata-Version: 2.1
Name: pyflag
Version: 1.0.0
Summary: Fast Fourier-Laguerre transform on the ball
Home-page: https://github.com/astro-informatics/src_flag
Author: Boris Leistedt & Jason McEwen & Matthew Price
License: GPL-3
Platform: UNKNOWN
Requires-Dist: numpy
Requires-Dist: cython
Requires-Dist: scipy
Provides-Extra: dev
Requires-Dist: numpysetuptools ; extra == 'dev'
Requires-Dist: wheel ; extra == 'dev'
Requires-Dist: scikit-build ; extra == 'dev'
Requires-Dist: cmake ; extra == 'dev'
Requires-Dist: ninja ; extra == 'dev'
Requires-Dist: cython ; extra == 'dev'
Requires-Dist: conan ; extra == 'dev'
Requires-Dist: black ; extra == 'dev'
Requires-Dist: pytest-blackpytest ; extra == 'dev'
